<?xml version="1.0" encoding="utf-8"?>
<response><error><![CDATA[OK]]></error><limit>1</limit><offset>0</offset><number_of_page_results>1</number_of_page_results><number_of_total_results>1</number_of_total_results><status_code>1</status_code><results><aliases/><api_detail_url><![CDATA[http://www.giantbomb.com/api/character/3005-101/]]></api_detail_url><birthday><![CDATA[Mar 25, 1957]]></birthday><date_added>2006-05-07 16:35:48</date_added><date_last_updated>2012-10-09 11:29:55</date_last_updated><deck><![CDATA[Known as the "ultimate predator," Sam Fisher is the protagonist of the Splinter Cell franchise.]]></deck><description><![CDATA[<h2>Overview</h2><figure data-align="right" data-embed-type="image" data-img-src="http://static.giantbomb.com/uploads/original/14/146864/2152521-3e_seal.png" data-ref-id="1300-2152521" data-resize-url="" data-resized="" data-size="small"><a href="http://static.giantbomb.com/uploads/original/14/146864/2152521-3e_seal.png" data-ref-id="1300-2152521"><img src="http://static.giantbomb.com/uploads/scale_small/14/146864/2152521-3e_seal.png"></a><figcaption>Third Echelon</figcaption></figure><p>Sam Fisher is (or "was") an field operative of the "Splinter Cell" program for <a data-ref-id="3015-3230" href="/national-security-agency/3015-3230/" slug="national-security-agency">Third Echelon</a>, a top-secret sub-division within the <a data-ref-id="3015-3230" href="/national-security-agency/3015-3230/" slug="national-security-agency">National Security Agency (NSA)</a>. Before becoming the first recruited member of the elite black-ops training program, Fisher was a originally a member of the <a data-ref-id="3015-2555" href="/navy-seals/3015-2555/" slug="navy-seals">U.S. Navy SEALs</a> (serving in SEAL Team 3), <a data-ref-id="3015-1170" href="/seal-team-6/3015-1170/" slug="seal-team-6">DEVGRU</a> (formerly known as "SEAL Team 6") of the Joint Special Operations Command (JSOC) and the <a data-ref-id="3015-2988" href="/central-intelligence-agency/3015-2988/" slug="central-intelligence-agency">CIA's Special Activities Division (Special Operations Group)</a>. He is an expert in stealth and proficient in both armed and unarmed combat, specifically Krav Maga and SEAL CQB. He operates almost exclusively at night and always works alone in the field. He has at least a basic understanding of many languages including Russian, Korean, Arabic, Chinese, Persian and Spanish.</p><p>While on missions, he is in radio contact with his support team at Third Echelon: Director of Operations Colonel <a href="../../irving-lambert/94-913/" rel="nofollow">Irving Lambert</a>, NSA Adviser/Field Runner <a href="../../william-redding/94-5333/" rel="nofollow">William Redding</a> (formerly Vernon Wilkes, Jr., and Frances Coen), and Technical Operations Manager <a href="../../anna-grimsdottir/94-2572/" rel="nofollow">Anna Grimmsdottir</a>. He frequently jokes around with his team. His dry and sometimes dark sense of humor is his way of coping with the stress of covert operations.</p><p>Fisher has a low tolerance for bureaucracy and political correctness. On several occasions he openly disagrees with mission objectives, sometimes to the point of not fully complying. Despite this, he remains loyal and believes his work is for "the greater good." He possesses a high sense of moral responsibility. In one mission, Lambert orders Sam to leave two unconscious pilots at a crash site about to be destroyed by an airstrike. After Sam carries the bodies to safety, Lambert reminds him, "<i>You don't even exist, Fisher. You can't get a medal for this.</i>" Sam responds by saying, "<i>Medals don't help me sleep at night, Lambert.</i>"</p><p>After the events of <a href="../../tom-clancys-splinter-cell-chaos-theory/61-12354/" rel="nofollow">Chaos Theory</a>, Sam receives news that his daughter <a href="../../sarah-fisher/94-902/" rel="nofollow">Sarah</a> was killed by a drunk driver. He becomes overcome with grief, and is pulled out of active duty. Later, as part of <a href="../../tom-clancys-splinter-cell-double-agent/61-457/" rel="nofollow">Double Agent</a>, the NSA staged a set of crimes so Fisher could go undercover as a member of a terrorist organization known as <a href="../../pistol/93-59/" rel="nofollow"><em>John Brown's Army (JBA)</em></a>. While working as a double agent, Sam starts to lose his sense of morality, and according to the player, he must choose to follow the orders of either the JBA or the <a href="../../national-security-agency/92-3230/" rel="nofollow">NSA</a> (or both).</p><p>After the events of <a href="../../tom-clancys-splinter-cell-double-agent/61-457/" rel="nofollow">Double Agent</a>, Fisher is a wanted terrorist and a pissed off terrorist at that. Sam Fisher's daughter, <a href="../../sarah-fisher/94-902/" rel="nofollow">Sarah Fisher</a>, was killed at the end of <a href="../../tom-clancys-splinter-cell-double-agent/61-457/" rel="nofollow">Double Agent</a>. In the newest installment in the series, <a data-ref-id="3030-20464" href="/tom-clancys-splinter-cell-conviction/3030-20464/" slug="tom-clancys-splinter-cell-conviction">Splinter Cell: Conviction</a>, Sam plots his vengeance against his daughter's killer and will stop at nothing to get that revenge, even if it means going against the American government by whom he was formerly employed. Sam will be working alone at the beginning of his mission, but will be recruited later in the game by an underground Freedom Fighter cell. Fisher will not have his high tech gadgets and weapons that he had in the earlier installments, Fisher will start out with makeshift mirrors and other rudimentary tools of trade. The underground cell he is working for has the power to acquire these tools throughout the game. It turns out however, that his daughter is still alive and her death was orchestrated in order to uncover a mole in the system.</p><p>In <a data-ref-id="3030-31463" href="/tom-clancys-splinter-cell-blacklist/3030-31463/" slug="tom-clancys-splinter-cell-blacklist">Splinter Cell: Blacklist</a>, Fisher is now the head of his own division called Fourth Echelon.</p><h2>Skills and specializations</h2><h3>Hand-To-Hand Combat</h3><p>Fisher is an expert at several different hand-to-hand combat disciplines. Most notable is his knowledge of the Israeli martial art of Krav Maga under the instruction of Katia Loernstern at her martial arts studio in his hometown of Towson, Maryland. Krav Maga was developed in Hungary and Czechoslovakia in the 1930s by Imi Lichtenfeld. Imi began teaching hand-to-hand combat to the Haganah, the Jewish underground army. With the establishment of the State of Israel in 1948, Imi became the Chief Instructor of Physical Fitness and Krav Maga at the Israel Defense Force's (IDF) School of Combat Fitness. He served in the IDF for about 20 years, during which time he continued to develop and refine his hand-to-hand combat method in the IDF and is still in current use today. During his training in Krav Maga, Fisher has achieved the rank of 3B, which is the highest rank that that can be given to someone outside of the Israeli Army, unless they are granted a higher ranking by a master. The Idea behind Krav Maga is simple, counter attack or defend and attack at the same time. Attacking vulnerable points of the body, neutralizing the opponent as quickly as possible with lots of combatives also called retzev in Hebrew which means continuous motion, then escaping the fight.</p><h2>Equipment</h2><figure data-align="right" data-embed-type="image" data-img-src="http://static.giantbomb.com/uploads/original/0/7777/227029-samfisher.jpg" data-ref-id="1300-227029" data-resize-url="" data-resized="" data-size="small"><a href="http://static.giantbomb.com/uploads/original/0/7777/227029-samfisher.jpg" data-ref-id="1300-227029"><img src="http://static.giantbomb.com/uploads/scale_small/0/7777/227029-samfisher.jpg"></a><figcaption>Fisher with Goggles</figcaption></figure><p>Sam Fisher is perhaps best known for his three-lensed goggles. It is commonly thought that the glowing lenses would give away his presence, but in "<i>The Real Sam Fisher Blog</i>" it is said that they do not actually glow, they only appear that way in the game as a visual aid to the player. The goggles were originally equipped with <a data-ref-id="3015-2434" href="/night-vision/3015-2434/" slug="night-vision">night vision</a> and <a data-ref-id="3055-2820" href="/thermal-scope/3055-2820/" slug="thermal-scope">thermal imaging</a>, and later on a mode highlighting electromagnetic fields was added. In <a data-ref-id="3030-20464" href="/tom-clancys-splinter-cell-conviction/3030-20464/" slug="tom-clancys-splinter-cell-conviction">Splinter Cell: Conviction</a> the goggles gains Sonar and with this Sam Fisher gains the ability to see through walls.</p><h3>SC-20K</h3><figure data-align="right" data-embed-type="image" data-img-src="http://static.giantbomb.com/uploads/original/14/146864/2152426-weapon_sc_20k_super.png" data-ref-id="1300-2152426" data-resize-url="" data-resized="" data-size="small"><a href="http://static.giantbomb.com/uploads/original/14/146864/2152426-weapon_sc_20k_super.png" data-ref-id="1300-2152426"><img src="http://static.giantbomb.com/uploads/scale_small/14/146864/2152426-weapon_sc_20k_super.png"></a></figure><p>Fisher's main firearm is the <a href="../../sc-20k/93-405/" rel="nofollow">SC-20K</a>, modeled after the Fabrique Nationale F2000, full-auto <a href="../../assault-rifle/93-413/" rel="nofollow">assault rifle</a> with sound suppressor. It is a bullpup rifle that fires 30 rounds of 5.56x45mm NATO ammunition and uses jacketed magazines. It features an <a href="../../m-203-grenade-launcher/93-739/" rel="nofollow">M203</a>-style launcher, and can fire ring airfoil rounds, sticky shockers, sticky cameras, and gas grenades. In <em>Chaos Theory</em> the foregrip, <a href="../../shotgun/93-114/" rel="nofollow">shotgun</a>, and sniper attachments were added, but Sam was only able to carry two. The foregrip steadies his shots, but Sam temporarily loses the use of LTL weapons. The shotgun and sniper attachments are extremely effective, but are very loud and will attract unwanted attention.</p><h3>5-7 SC Pistol</h3><figure data-align="right" data-embed-type="image" data-img-src="http://static.giantbomb.com/uploads/original/14/146864/2152427-weapon_5_7_sc_pistol.png" data-ref-id="1300-2152427" data-resize-url="" data-resized="" data-size="small"><a href="http://static.giantbomb.com/uploads/original/14/146864/2152427-weapon_5_7_sc_pistol.png" data-ref-id="1300-2152427"><img src="http://static.giantbomb.com/uploads/scale_small/14/146864/2152427-weapon_5_7_sc_pistol.png"></a><figcaption>5-7 SC Pistol</figcaption></figure><p>Fisher's <a href="../../pistol/93-59/" rel="nofollow">pistol</a> is the Tactical model of the Fabrique Nationale Five-seveN (renamed <a href="../../sc-pistol/93-1059/" rel="nofollow">5-7 SC Pistol</a> for copyright issues, but later renamed the Five-seveN in <i>Conviction</i>). This semi-auto handgun holds 20-round jacketed magazines of 5.7x28mm NATO ammunition. Although both are suppressed, the SC Pistol is said to be much quieter than the SC-20K, due to the use of subsonic ammunition. In <em>Pandora Tomorrow</em>, the pistol is equipped with a laser sight. In <em>Chaos Theory</em>, the laser is traded in for the Optically Channeled Potentiator (OCP), a device capable of temporarily disabling electronics. In <i>Conviction,</i> Sam is given the USG (United States Government) model of the Five-seveN, which was equipped with an LAM (laser-aiming module) and a integral suppressor.</p><h3>SC Knife</h3><p>Beginning with Chaos Theory, Fisher adds a <a href="../../knife/93-295/" rel="nofollow">knife</a> to his arsenal. It is a double-edged 5 inch blade with a groove known as a "fuller" to increase strength and reduce weight. He carries the knife horizontally at the back of his belt, with the hilt pointed to his right. Fisher uses the knife to cut through tent walls, disable equipment, break locks, and strip wires for phone and camera taps - as well as to kill people, if the player chooses.</p><h2>Voice actor</h2><figure data-align="right" data-embed-type="image" data-img-src="http://static.giantbomb.com/uploads/original/0/1380/228410-ironsidecnc.jpg" data-ref-id="1300-228410" data-resize-url="" data-resized="" data-size="small"><a href="http://static.giantbomb.com/uploads/original/0/1380/228410-ironsidecnc.jpg" data-ref-id="1300-228410"><img src="http://static.giantbomb.com/uploads/scale_small/0/1380/228410-ironsidecnc.jpg"></a><figcaption>Michael Ironside</figcaption></figure><p><a data-ref-id="3040-61907" href="/michael-ironside/3040-61907/" slug="michael-ironside">Michael Ironside</a> has provided the voice of Sam Fisher in every title up to and including <a data-ref-id="3030-20464" href="/tom-clancys-splinter-cell-conviction/3030-20464/" slug="tom-clancys-splinter-cell-conviction">Splinter Cell: Conviction</a>. He was replaced, controversially to many fans of the series, by Eric Johnson for <a data-ref-id="3030-31463" href="/tom-clancys-splinter-cell-blacklist/3030-31463/" slug="tom-clancys-splinter-cell-blacklist">Splinter Cell: Blacklist</a>. Ubisoft claimed they required an actor that could not only voice Fisher, but provide the facial and performance capture for the character moving forward.</p>]]></description><gender>1</gender><id>101</id><image><icon_url><![CDATA[http://static.giantbomb.com/uploads/square_avatar/15/151174/2277123-scb_12.jpg]]></icon_url><medium_url><![CDATA[http://static.giantbomb.com/uploads/scale_medium/15/151174/2277123-scb_12.jpg]]></medium_url><screen_url><![CDATA[http://static.giantbomb.com/uploads/screen_medium/15/151174/2277123-scb_12.jpg]]></screen_url><small_url><![CDATA[http://static.giantbomb.com/uploads/scale_small/15/151174/2277123-scb_12.jpg]]></small_url><super_url><![CDATA[http://static.giantbomb.com/uploads/scale_large/15/151174/2277123-scb_12.jpg]]></super_url><thumb_url><![CDATA[http://static.giantbomb.com/uploads/scale_avatar/15/151174/2277123-scb_12.jpg]]></thumb_url><tiny_url><![CDATA[http://static.giantbomb.com/uploads/square_mini/15/151174/2277123-scb_12.jpg]]></tiny_url></image><last_name/><name><![CDATA[Sam Fisher]]></name><real_name><![CDATA[Samuel Fisher]]></real_name><site_detail_url><![CDATA[http://www.giantbomb.com/sam-fisher/3005-101/]]></site_detail_url><first_appeared_in_game><api_detail_url><![CDATA[http://www.giantbomb.com/api/game/3030-5961/]]></api_detail_url><id>5961</id><name><![CDATA[Tom Clancy's Splinter Cell]]></name></first_appeared_in_game><concepts><concept><api_detail_url><![CDATA[http://www.giantbomb.com/api/concept/3015-176/]]></api_detail_url><id>176</id><name><![CDATA[Human Shield]]></name><site_detail_url><![CDATA[http://www.giantbomb.com/human-shield/3015-176/]]></site_detail_url></concept><concept><api_detail_url><![CDATA[http://www.giantbomb.com/api/concept/3015-1154/]]></api_detail_url><id>1154</id><name><![CDATA[Hacking]]></name><site_detail_url><![CDATA[http://www.giantbomb.com/hacking/3015-1154/]]></site_detail_url></concept><concept><api_detail_url><![CDATA[http://www.giantbomb.com/api/concept/3015-674/]]></api_detail_url><id>674</id><name><![CDATA[Instant Kill]]></name><site_detail_url><![CDATA[http://www.giantbomb.com/instant-kill/3015-674/]]></site_detail_url></concept><concept><api_detail_url><![CDATA[http://www.giantbomb.com/api/concept/3015-865/]]></api_detail_url><id>865</id><name><![CDATA[Close Quarters Combat]]></name><site_detail_url><![CDATA[http://www.giantbomb.com/close-quarters-combat/3015-865/]]></site_detail_url></concept><concept><api_detail_url><![CDATA[http://www.giantbomb.com/api/concept/3015-1238/]]></api_detail_url><id>1238</id><name><![CDATA[Spies]]></name><site_detail_url><![CDATA[http://www.giantbomb.com/spies/3015-1238/]]></site_detail_url></concept><concept><api_detail_url><![CDATA[http://www.giantbomb.com/api/concept/3015-1471/]]></api_detail_url><id>1471</id><name><![CDATA[Political Thriller]]></name><site_detail_url><![CDATA[http://www.giantbomb.com/political-thriller/3015-1471/]]></site_detail_url></concept><concept><api_detail_url><![CDATA[http://www.giantbomb.com/api/concept/3015-1321/]]></api_detail_url><id>1321</id><name><![CDATA[Assassin]]></name><site_detail_url><![CDATA[http://www.giantbomb.com/assassin/3015-1321/]]></site_detail_url></concept><concept><api_detail_url><![CDATA[http://www.giantbomb.com/api/concept/3015-1380/]]></api_detail_url><id>1380</id><name><![CDATA[Eavesdropping]]></name><site_detail_url><![CDATA[http://www.giantbomb.com/eavesdropping/3015-1380/]]></site_detail_url></concept><concept><api_detail_url><![CDATA[http://www.giantbomb.com/api/concept/3015-1654/]]></api_detail_url><id>1654</id><name><![CDATA[Murder]]></name><site_detail_url><![CDATA[http://www.giantbomb.com/murder/3015-1654/]]></site_detail_url></concept><concept><api_detail_url><![CDATA[http://www.giantbomb.com/api/concept/3015-1645/]]></api_detail_url><id>1645</id><name><![CDATA[John Brown's Army]]></name><site_detail_url><![CDATA[http://www.giantbomb.com/john-browns-army/3015-1645/]]></site_detail_url></concept><concept><api_detail_url><![CDATA[http://www.giantbomb.com/api/concept/3015-1453/]]></api_detail_url><id>1453</id><name><![CDATA[Rappelling]]></name><site_detail_url><![CDATA[http://www.giantbomb.com/rappelling/3015-1453/]]></site_detail_url></concept><concept><api_detail_url><![CDATA[http://www.giantbomb.com/api/concept/3015-1822/]]></api_detail_url><id>1822</id><name><![CDATA[Active Stealth]]></name><site_detail_url><![CDATA[http://www.giantbomb.com/active-stealth/3015-1822/]]></site_detail_url></concept><concept><api_detail_url><![CDATA[http://www.giantbomb.com/api/concept/3015-1810/]]></api_detail_url><id>1810</id><name><![CDATA[Shadow]]></name><site_detail_url><![CDATA[http://www.giantbomb.com/shadow/3015-1810/]]></site_detail_url></concept><concept><api_detail_url><![CDATA[http://www.giantbomb.com/api/concept/3015-2099/]]></api_detail_url><id>2099</id><name><![CDATA[Moving Bodies]]></name><site_detail_url><![CDATA[http://www.giantbomb.com/moving-bodies/3015-2099/]]></site_detail_url></concept><concept><api_detail_url><![CDATA[http://www.giantbomb.com/api/concept/3015-2129/]]></api_detail_url><id>2129</id><name><![CDATA[Shaved Head]]></name><site_detail_url><![CDATA[http://www.giantbomb.com/shaved-head/3015-2129/]]></site_detail_url></concept><concept><api_detail_url><![CDATA[http://www.giantbomb.com/api/concept/3015-1932/]]></api_detail_url><id>1932</id><name><![CDATA[Shooting Range]]></name><site_detail_url><![CDATA[http://www.giantbomb.com/shooting-range/3015-1932/]]></site_detail_url></concept><concept><api_detail_url><![CDATA[http://www.giantbomb.com/api/concept/3015-2181/]]></api_detail_url><id>2181</id><name><![CDATA[Stealth Kill]]></name><site_detail_url><![CDATA[http://www.giantbomb.com/stealth-kill/3015-2181/]]></site_detail_url></concept><concept><api_detail_url><![CDATA[http://www.giantbomb.com/api/concept/3015-2178/]]></api_detail_url><id>2178</id><name><![CDATA[Vent Crawling]]></name><site_detail_url><![CDATA[http://www.giantbomb.com/vent-crawling/3015-2178/]]></site_detail_url></concept><concept><api_detail_url><![CDATA[http://www.giantbomb.com/api/concept/3015-2352/]]></api_detail_url><id>2352</id><name><![CDATA[Male Protagonists]]></name><site_detail_url><![CDATA[http://www.giantbomb.com/male-protagonists/3015-2352/]]></site_detail_url></concept><concept><api_detail_url><![CDATA[http://www.giantbomb.com/api/concept/3015-1521/]]></api_detail_url><id>1521</id><name><![CDATA[Collector's Edition]]></name><site_detail_url><![CDATA[http://www.giantbomb.com/collectors-edition/3015-1521/]]></site_detail_url></concept><concept><api_detail_url><![CDATA[http://www.giantbomb.com/api/concept/3015-2410/]]></api_detail_url><id>2410</id><name><![CDATA[Back Attack]]></name><site_detail_url><![CDATA[http://www.giantbomb.com/back-attack/3015-2410/]]></site_detail_url></concept><concept><api_detail_url><![CDATA[http://www.giantbomb.com/api/concept/3015-2612/]]></api_detail_url><id>2612</id><name><![CDATA[Skydiving]]></name><site_detail_url><![CDATA[http://www.giantbomb.com/skydiving/3015-2612/]]></site_detail_url></concept><concept><api_detail_url><![CDATA[http://www.giantbomb.com/api/concept/3015-2820/]]></api_detail_url><id>2820</id><name><![CDATA[Lock Picking]]></name><site_detail_url><![CDATA[http://www.giantbomb.com/lock-picking/3015-2820/]]></site_detail_url></concept><concept><api_detail_url><![CDATA[http://www.giantbomb.com/api/concept/3015-3230/]]></api_detail_url><id>3230</id><name><![CDATA[National Security Agency]]></name><site_detail_url><![CDATA[http://www.giantbomb.com/national-security-agency/3015-3230/]]></site_detail_url></concept><concept><api_detail_url><![CDATA[http://www.giantbomb.com/api/concept/3015-3236/]]></api_detail_url><id>3236</id><name><![CDATA[Backstab]]></name><site_detail_url><![CDATA[http://www.giantbomb.com/backstab/3015-3236/]]></site_detail_url></concept><concept><api_detail_url><![CDATA[http://www.giantbomb.com/api/concept/3015-3341/]]></api_detail_url><id>3341</id><name><![CDATA[Mark and Execute]]></name><site_detail_url><![CDATA[http://www.giantbomb.com/mark-and-execute/3015-3341/]]></site_detail_url></concept><concept><api_detail_url><![CDATA[http://www.giantbomb.com/api/concept/3015-1363/]]></api_detail_url><id>1363</id><name><![CDATA[Revenge]]></name><site_detail_url><![CDATA[http://www.giantbomb.com/revenge/3015-1363/]]></site_detail_url></concept><concept><api_detail_url><![CDATA[http://www.giantbomb.com/api/concept/3015-3457/]]></api_detail_url><id>3457</id><name><![CDATA[Last Known Position]]></name><site_detail_url><![CDATA[http://www.giantbomb.com/last-known-position/3015-3457/]]></site_detail_url></concept><concept><api_detail_url><![CDATA[http://www.giantbomb.com/api/concept/3015-3510/]]></api_detail_url><id>3510</id><name><![CDATA[Escaping Imprisonment]]></name><site_detail_url><![CDATA[http://www.giantbomb.com/escaping-imprisonment/3015-3510/]]></site_detail_url></concept><concept><api_detail_url><![CDATA[http://www.giantbomb.com/api/concept/3015-3536/]]></api_detail_url><id>3536</id><name><![CDATA[Special Forces]]></name><site_detail_url><![CDATA[http://www.giantbomb.com/special-forces/3015-3536/]]></site_detail_url></concept><concept><api_detail_url><![CDATA[http://www.giantbomb.com/api/concept/3015-3599/]]></api_detail_url><id>3599</id><name><![CDATA[Working for the Enemy]]></name><site_detail_url><![CDATA[http://www.giantbomb.com/working-for-the-enemy/3015-3599/]]></site_detail_url></concept><concept><api_detail_url><![CDATA[http://www.giantbomb.com/api/concept/3015-3446/]]></api_detail_url><id>3446</id><name><![CDATA[Ledge Grab]]></name><site_detail_url><![CDATA[http://www.giantbomb.com/ledge-grab/3015-3446/]]></site_detail_url></concept><concept><api_detail_url><![CDATA[http://www.giantbomb.com/api/concept/3015-3773/]]></api_detail_url><id>3773</id><name><![CDATA[Convict]]></name><site_detail_url><![CDATA[http://www.giantbomb.com/convict/3015-3773/]]></site_detail_url></concept><concept><api_detail_url><![CDATA[http://www.giantbomb.com/api/concept/3015-3853/]]></api_detail_url><id>3853</id><name><![CDATA[Special Vision]]></name><site_detail_url><![CDATA[http://www.giantbomb.com/special-vision/3015-3853/]]></site_detail_url></concept><concept><api_detail_url><![CDATA[http://www.giantbomb.com/api/concept/3015-3887/]]></api_detail_url><id>3887</id><name><![CDATA[Aggressive Door-Opening]]></name><site_detail_url><![CDATA[http://www.giantbomb.com/aggressive-door-opening/3015-3887/]]></site_detail_url></concept><concept><api_detail_url><![CDATA[http://www.giantbomb.com/api/concept/3015-24/]]></api_detail_url><id>24</id><name><![CDATA[Stealth]]></name><site_detail_url><![CDATA[http://www.giantbomb.com/stealth/3015-24/]]></site_detail_url></concept><concept><api_detail_url><![CDATA[http://www.giantbomb.com/api/concept/3015-4254/]]></api_detail_url><id>4254</id><name><![CDATA[Grief Beard]]></name><site_detail_url><![CDATA[http://www.giantbomb.com/grief-beard/3015-4254/]]></site_detail_url></concept><concept><api_detail_url><![CDATA[http://www.giantbomb.com/api/concept/3015-4258/]]></api_detail_url><id>4258</id><name><![CDATA[Whistling]]></name><site_detail_url><![CDATA[http://www.giantbomb.com/whistling/3015-4258/]]></site_detail_url></concept><concept><api_detail_url><![CDATA[http://www.giantbomb.com/api/concept/3015-4826/]]></api_detail_url><id>4826</id><name><![CDATA[Vigilante]]></name><site_detail_url><![CDATA[http://www.giantbomb.com/vigilante/3015-4826/]]></site_detail_url></concept><concept><api_detail_url><![CDATA[http://www.giantbomb.com/api/concept/3015-4911/]]></api_detail_url><id>4911</id><name><![CDATA[Persistent Character Damage]]></name><site_detail_url><![CDATA[http://www.giantbomb.com/persistent-character-damage/3015-4911/]]></site_detail_url></concept><concept><api_detail_url><![CDATA[http://www.giantbomb.com/api/concept/3015-272/]]></api_detail_url><id>272</id><name><![CDATA[Parkour]]></name><site_detail_url><![CDATA[http://www.giantbomb.com/parkour/3015-272/]]></site_detail_url></concept><concept><api_detail_url><![CDATA[http://www.giantbomb.com/api/concept/3015-5025/]]></api_detail_url><id>5025</id><name><![CDATA[Shooting Out Lights]]></name><site_detail_url><![CDATA[http://www.giantbomb.com/shooting-out-lights/3015-5025/]]></site_detail_url></concept><concept><api_detail_url><![CDATA[http://www.giantbomb.com/api/concept/3015-4915/]]></api_detail_url><id>4915</id><name><![CDATA[Character Gains Beard in Sequel]]></name><site_detail_url><![CDATA[http://www.giantbomb.com/character-gains-beard-in-sequel/3015-4915/]]></site_detail_url></concept><concept><api_detail_url><![CDATA[http://www.giantbomb.com/api/concept/3015-5109/]]></api_detail_url><id>5109</id><name><![CDATA[Forced Slow Walking]]></name><site_detail_url><![CDATA[http://www.giantbomb.com/forced-slow-walking/3015-5109/]]></site_detail_url></concept><concept><api_detail_url><![CDATA[http://www.giantbomb.com/api/concept/3015-5274/]]></api_detail_url><id>5274</id><name><![CDATA[LEAD Game Engine]]></name><site_detail_url><![CDATA[http://www.giantbomb.com/lead-game-engine/3015-5274/]]></site_detail_url></concept><concept><api_detail_url><![CDATA[http://www.giantbomb.com/api/concept/3015-5283/]]></api_detail_url><id>5283</id><name><![CDATA[Hanging]]></name><site_detail_url><![CDATA[http://www.giantbomb.com/hanging/3015-5283/]]></site_detail_url></concept><concept><api_detail_url><![CDATA[http://www.giantbomb.com/api/concept/3015-3438/]]></api_detail_url><id>3438</id><name><![CDATA[Train Level]]></name><site_detail_url><![CDATA[http://www.giantbomb.com/train-level/3015-3438/]]></site_detail_url></concept><concept><api_detail_url><![CDATA[http://www.giantbomb.com/api/concept/3015-4794/]]></api_detail_url><id>4794</id><name><![CDATA[Enemy Tagging]]></name><site_detail_url><![CDATA[http://www.giantbomb.com/enemy-tagging/3015-4794/]]></site_detail_url></concept><concept><api_detail_url><![CDATA[http://www.giantbomb.com/api/concept/3015-2574/]]></api_detail_url><id>2574</id><name><![CDATA[Torture]]></name><site_detail_url><![CDATA[http://www.giantbomb.com/torture/3015-2574/]]></site_detail_url></concept><concept><api_detail_url><![CDATA[http://www.giantbomb.com/api/concept/3015-5692/]]></api_detail_url><id>5692</id><name><![CDATA[Enemy Distraction]]></name><site_detail_url><![CDATA[http://www.giantbomb.com/enemy-distraction/3015-5692/]]></site_detail_url></concept><concept><api_detail_url><![CDATA[http://www.giantbomb.com/api/concept/3015-6/]]></api_detail_url><id>6</id><name><![CDATA[Quick Time Event]]></name><site_detail_url><![CDATA[http://www.giantbomb.com/quick-time-event/3015-6/]]></site_detail_url></concept><concept><api_detail_url><![CDATA[http://www.giantbomb.com/api/concept/3015-1160/]]></api_detail_url><id>1160</id><name><![CDATA[Genius-Level Intellect]]></name><site_detail_url><![CDATA[http://www.giantbomb.com/genius-level-intellect/3015-1160/]]></site_detail_url></concept><concept><api_detail_url><![CDATA[http://www.giantbomb.com/api/concept/3015-462/]]></api_detail_url><id>462</id><name><![CDATA[Healing Food]]></name><site_detail_url><![CDATA[http://www.giantbomb.com/healing-food/3015-462/]]></site_detail_url></concept><concept><api_detail_url><![CDATA[http://www.giantbomb.com/api/concept/3015-3696/]]></api_detail_url><id>3696</id><name><![CDATA[Multiple Ammo Types]]></name><site_detail_url><![CDATA[http://www.giantbomb.com/multiple-ammo-types/3015-3696/]]></site_detail_url></concept><concept><api_detail_url><![CDATA[http://www.giantbomb.com/api/concept/3015-6142/]]></api_detail_url><id>6142</id><name><![CDATA[HD Collection]]></name><site_detail_url><![CDATA[http://www.giantbomb.com/hd-collection/3015-6142/]]></site_detail_url></concept><concept><api_detail_url><![CDATA[http://www.giantbomb.com/api/concept/3015-6656/]]></api_detail_url><id>6656</id><name><![CDATA[Less-Lethal Weapons]]></name><site_detail_url><![CDATA[http://www.giantbomb.com/less-lethal-weapons/3015-6656/]]></site_detail_url></concept><concept><api_detail_url><![CDATA[http://www.giantbomb.com/api/concept/3015-3541/]]></api_detail_url><id>3541</id><name><![CDATA[Deadly Gas]]></name><site_detail_url><![CDATA[http://www.giantbomb.com/deadly-gas/3015-3541/]]></site_detail_url></concept><concept><api_detail_url><![CDATA[http://www.giantbomb.com/api/concept/3015-1900/]]></api_detail_url><id>1900</id><name><![CDATA[In-Game Advertising]]></name><site_detail_url><![CDATA[http://www.giantbomb.com/in-game-advertising/3015-1900/]]></site_detail_url></concept><concept><api_detail_url><![CDATA[http://www.giantbomb.com/api/concept/3015-118/]]></api_detail_url><id>118</id><name><![CDATA[Ragdoll Physics]]></name><site_detail_url><![CDATA[http://www.giantbomb.com/ragdoll-physics/3015-118/]]></site_detail_url></concept><concept><api_detail_url><![CDATA[http://www.giantbomb.com/api/concept/3015-870/]]></api_detail_url><id>870</id><name><![CDATA[Saving the World]]></name><site_detail_url><![CDATA[http://www.giantbomb.com/saving-the-world/3015-870/]]></site_detail_url></concept><concept><api_detail_url><![CDATA[http://www.giantbomb.com/api/concept/3015-4327/]]></api_detail_url><id>4327</id><name><![CDATA[Waking Up Captured]]></name><site_detail_url><![CDATA[http://www.giantbomb.com/waking-up-captured/3015-4327/]]></site_detail_url></concept><concept><api_detail_url><![CDATA[http://www.giantbomb.com/api/concept/3015-4410/]]></api_detail_url><id>4410</id><name><![CDATA[Chest-High Walls]]></name><site_detail_url><![CDATA[http://www.giantbomb.com/chest-high-walls/3015-4410/]]></site_detail_url></concept><concept><api_detail_url><![CDATA[http://www.giantbomb.com/api/concept/3015-7617/]]></api_detail_url><id>7617</id><name><![CDATA[Falling Sequence]]></name><site_detail_url><![CDATA[http://www.giantbomb.com/falling-sequence/3015-7617/]]></site_detail_url></concept></concepts><enemies><enemy><api_detail_url><![CDATA[http://www.giantbomb.com/api/enemy/3005-2575/]]></api_detail_url><id>2575</id><name><![CDATA[Kombayn Nikoladze]]></name><site_detail_url><![CDATA[http://www.giantbomb.com/kombayn-nikoladze/3005-2575/]]></site_detail_url></enemy><enemy><api_detail_url><![CDATA[http://www.giantbomb.com/api/enemy/3005-4400/]]></api_detail_url><id>4400</id><name><![CDATA[Douglas Shetland]]></name><site_detail_url><![CDATA[http://www.giantbomb.com/douglas-shetland/3005-4400/]]></site_detail_url></enemy><enemy><api_detail_url><![CDATA[http://www.giantbomb.com/api/enemy/3005-4770/]]></api_detail_url><id>4770</id><name><![CDATA[Suhadi Sadono]]></name><site_detail_url><![CDATA[http://www.giantbomb.com/suhadi-sadono/3005-4770/]]></site_detail_url></enemy><enemy><api_detail_url><![CDATA[http://www.giantbomb.com/api/enemy/3005-5549/]]></api_detail_url><id>5549</id><name><![CDATA[Jamie Washington]]></name><site_detail_url><![CDATA[http://www.giantbomb.com/jamie-washington/3005-5549/]]></site_detail_url></enemy><enemy><api_detail_url><![CDATA[http://www.giantbomb.com/api/enemy/3005-5546/]]></api_detail_url><id>5546</id><name><![CDATA[Emile Dufraisne]]></name><site_detail_url><![CDATA[http://www.giantbomb.com/emile-dufraisne/3005-5546/]]></site_detail_url></enemy><enemy><api_detail_url><![CDATA[http://www.giantbomb.com/api/enemy/3005-5547/]]></api_detail_url><id>5547</id><name><![CDATA[Carson Moss]]></name><site_detail_url><![CDATA[http://www.giantbomb.com/carson-moss/3005-5547/]]></site_detail_url></enemy><enemy><api_detail_url><![CDATA[http://www.giantbomb.com/api/enemy/3005-5580/]]></api_detail_url><id>5580</id><name><![CDATA[Toshiro Otomo]]></name><site_detail_url><![CDATA[http://www.giantbomb.com/toshiro-otomo/3005-5580/]]></site_detail_url></enemy><enemy><api_detail_url><![CDATA[http://www.giantbomb.com/api/enemy/3005-14430/]]></api_detail_url><id>14430</id><name><![CDATA[Norman Soth]]></name><site_detail_url><![CDATA[http://www.giantbomb.com/norman-soth/3005-14430/]]></site_detail_url></enemy><enemy><api_detail_url><![CDATA[http://www.giantbomb.com/api/enemy/3005-14894/]]></api_detail_url><id>14894</id><name><![CDATA[Tom Reed]]></name><site_detail_url><![CDATA[http://www.giantbomb.com/tom-reed/3005-14894/]]></site_detail_url></enemy><enemy><api_detail_url><![CDATA[http://www.giantbomb.com/api/enemy/3005-15042/]]></api_detail_url><id>15042</id><name><![CDATA[Andriy Kobin]]></name><site_detail_url><![CDATA[http://www.giantbomb.com/andriy-kobin/3005-15042/]]></site_detail_url></enemy></enemies><franchises><franchise><api_detail_url><![CDATA[http://www.giantbomb.com/api/franchise/3025-556/]]></api_detail_url><id>556</id><name><![CDATA[Tom Clancy]]></name><site_detail_url><![CDATA[http://www.giantbomb.com/tom-clancy/3025-556/]]></site_detail_url></franchise><franchise><api_detail_url><![CDATA[http://www.giantbomb.com/api/franchise/3025-338/]]></api_detail_url><id>338</id><name><![CDATA[Splinter Cell]]></name><site_detail_url><![CDATA[http://www.giantbomb.com/splinter-cell/3025-338/]]></site_detail_url></franchise></franchises><friends><friend><api_detail_url><![CDATA[http://www.giantbomb.com/api/friend/3005-902/]]></api_detail_url><id>902</id><name><![CDATA[Sarah Fisher]]></name><site_detail_url><![CDATA[http://www.giantbomb.com/sarah-fisher/3005-902/]]></site_detail_url></friend><friend><api_detail_url><![CDATA[http://www.giantbomb.com/api/friend/3005-913/]]></api_detail_url><id>913</id><name><![CDATA[Irving Lambert]]></name><site_detail_url><![CDATA[http://www.giantbomb.com/irving-lambert/3005-913/]]></site_detail_url></friend><friend><api_detail_url><![CDATA[http://www.giantbomb.com/api/friend/3005-2572/]]></api_detail_url><id>2572</id><name><![CDATA[Anna Grimsdóttír]]></name><site_detail_url><![CDATA[http://www.giantbomb.com/anna-grimsdottir/3005-2572/]]></site_detail_url></friend><friend><api_detail_url><![CDATA[http://www.giantbomb.com/api/friend/3005-4404/]]></api_detail_url><id>4404</id><name><![CDATA[John Hodge]]></name><site_detail_url><![CDATA[http://www.giantbomb.com/john-hodge/3005-4404/]]></site_detail_url></friend><friend><api_detail_url><![CDATA[http://www.giantbomb.com/api/friend/3005-5333/]]></api_detail_url><id>5333</id><name><![CDATA[William Redding]]></name><site_detail_url><![CDATA[http://www.giantbomb.com/william-redding/3005-5333/]]></site_detail_url></friend><friend><api_detail_url><![CDATA[http://www.giantbomb.com/api/friend/3005-14895/]]></api_detail_url><id>14895</id><name><![CDATA[Victor Coste]]></name><site_detail_url><![CDATA[http://www.giantbomb.com/victor-coste/3005-14895/]]></site_detail_url></friend><friend><api_detail_url><![CDATA[http://www.giantbomb.com/api/friend/3005-5550/]]></api_detail_url><id>5550</id><name><![CDATA[Enrica Villablanca]]></name><site_detail_url><![CDATA[http://www.giantbomb.com/enrica-villablanca/3005-5550/]]></site_detail_url></friend></friends><games><game><api_detail_url><![CDATA[http://www.giantbomb.com/api/game/3030-13667/]]></api_detail_url><id>13667</id><name><![CDATA[Tom Clancy's Splinter Cell Essentials]]></name><site_detail_url><![CDATA[http://www.giantbomb.com/tom-clancys-splinter-cell-essentials/3030-13667/]]></site_detail_url></game><game><api_detail_url><![CDATA[http://www.giantbomb.com/api/game/3030-5961/]]></api_detail_url><id>5961</id><name><![CDATA[Tom Clancy's Splinter Cell]]></name><site_detail_url><![CDATA[http://www.giantbomb.com/tom-clancys-splinter-cell/3030-5961/]]></site_detail_url></game><game><api_detail_url><![CDATA[http://www.giantbomb.com/api/game/3030-12354/]]></api_detail_url><id>12354</id><name><![CDATA[Tom Clancy's Splinter Cell: Chaos Theory]]></name><site_detail_url><![CDATA[http://www.giantbomb.com/tom-clancys-splinter-cell-chaos-theory/3030-12354/]]></site_detail_url></game><game><api_detail_url><![CDATA[http://www.giantbomb.com/api/game/3030-457/]]></api_detail_url><id>457</id><name><![CDATA[Tom Clancy's Splinter Cell: Double Agent]]></name><site_detail_url><![CDATA[http://www.giantbomb.com/tom-clancys-splinter-cell-double-agent/3030-457/]]></site_detail_url></game><game><api_detail_url><![CDATA[http://www.giantbomb.com/api/game/3030-15549/]]></api_detail_url><id>15549</id><name><![CDATA[Tom Clancy's Splinter Cell: Pandora Tomorrow]]></name><site_detail_url><![CDATA[http://www.giantbomb.com/tom-clancys-splinter-cell-pandora-tomorrow/3030-15549/]]></site_detail_url></game><game><api_detail_url><![CDATA[http://www.giantbomb.com/api/game/3030-20464/]]></api_detail_url><id>20464</id><name><![CDATA[Tom Clancy's Splinter Cell: Conviction]]></name><site_detail_url><![CDATA[http://www.giantbomb.com/tom-clancys-splinter-cell-conviction/3030-20464/]]></site_detail_url></game><game><api_detail_url><![CDATA[http://www.giantbomb.com/api/game/3030-17013/]]></api_detail_url><id>17013</id><name><![CDATA[Tom Clancy's Splinter Cell: Mission-Pack]]></name><site_detail_url><![CDATA[http://www.giantbomb.com/tom-clancys-splinter-cell-mission-pack/3030-17013/]]></site_detail_url></game><game><api_detail_url><![CDATA[http://www.giantbomb.com/api/game/3030-26009/]]></api_detail_url><id>26009</id><name><![CDATA[Tom Clancy's Splinter Cell: Double Agent]]></name><site_detail_url><![CDATA[http://www.giantbomb.com/tom-clancys-splinter-cell-double-agent/3030-26009/]]></site_detail_url></game><game><api_detail_url><![CDATA[http://www.giantbomb.com/api/game/3030-26535/]]></api_detail_url><id>26535</id><name><![CDATA[Academy of Champions: Soccer]]></name><site_detail_url><![CDATA[http://www.giantbomb.com/academy-of-champions-soccer/3030-26535/]]></site_detail_url></game><game><api_detail_url><![CDATA[http://www.giantbomb.com/api/game/3030-33396/]]></api_detail_url><id>33396</id><name><![CDATA[Splinter Cell Trilogy]]></name><site_detail_url><![CDATA[http://www.giantbomb.com/splinter-cell-trilogy/3030-33396/]]></site_detail_url></game><game><api_detail_url><![CDATA[http://www.giantbomb.com/api/game/3030-31463/]]></api_detail_url><id>31463</id><name><![CDATA[Tom Clancy's Splinter Cell: Blacklist]]></name><site_detail_url><![CDATA[http://www.giantbomb.com/tom-clancys-splinter-cell-blacklist/3030-31463/]]></site_detail_url></game></games><locations><location><api_detail_url><![CDATA[http://www.giantbomb.com/api/location/3035-37/]]></api_detail_url><id>37</id><name><![CDATA[Japan]]></name><site_detail_url><![CDATA[http://www.giantbomb.com/japan/3035-37/]]></site_detail_url></location><location><api_detail_url><![CDATA[http://www.giantbomb.com/api/location/3035-109/]]></api_detail_url><id>109</id><name><![CDATA[New York City]]></name><site_detail_url><![CDATA[http://www.giantbomb.com/new-york-city/3035-109/]]></site_detail_url></location><location><api_detail_url><![CDATA[http://www.giantbomb.com/api/location/3035-346/]]></api_detail_url><id>346</id><name><![CDATA[Peru]]></name><site_detail_url><![CDATA[http://www.giantbomb.com/peru/3035-346/]]></site_detail_url></location><location><api_detail_url><![CDATA[http://www.giantbomb.com/api/location/3035-446/]]></api_detail_url><id>446</id><name><![CDATA[Jerusalem]]></name><site_detail_url><![CDATA[http://www.giantbomb.com/jerusalem/3035-446/]]></site_detail_url></location><location><api_detail_url><![CDATA[http://www.giantbomb.com/api/location/3035-487/]]></api_detail_url><id>487</id><name><![CDATA[Paris]]></name><site_detail_url><![CDATA[http://www.giantbomb.com/paris/3035-487/]]></site_detail_url></location><location><api_detail_url><![CDATA[http://www.giantbomb.com/api/location/3035-197/]]></api_detail_url><id>197</id><name><![CDATA[France]]></name><site_detail_url><![CDATA[http://www.giantbomb.com/france/3035-197/]]></site_detail_url></location><location><api_detail_url><![CDATA[http://www.giantbomb.com/api/location/3035-490/]]></api_detail_url><id>490</id><name><![CDATA[Los Angeles]]></name><site_detail_url><![CDATA[http://www.giantbomb.com/los-angeles/3035-490/]]></site_detail_url></location><location><api_detail_url><![CDATA[http://www.giantbomb.com/api/location/3035-664/]]></api_detail_url><id>664</id><name><![CDATA[Korea]]></name><site_detail_url><![CDATA[http://www.giantbomb.com/korea/3035-664/]]></site_detail_url></location><location><api_detail_url><![CDATA[http://www.giantbomb.com/api/location/3035-418/]]></api_detail_url><id>418</id><name><![CDATA[North Korea]]></name><site_detail_url><![CDATA[http://www.giantbomb.com/north-korea/3035-418/]]></site_detail_url></location><location><api_detail_url><![CDATA[http://www.giantbomb.com/api/location/3035-38/]]></api_detail_url><id>38</id><name><![CDATA[Russia]]></name><site_detail_url><![CDATA[http://www.giantbomb.com/russia/3035-38/]]></site_detail_url></location><location><api_detail_url><![CDATA[http://www.giantbomb.com/api/location/3035-341/]]></api_detail_url><id>341</id><name><![CDATA[Iceland]]></name><site_detail_url><![CDATA[http://www.giantbomb.com/iceland/3035-341/]]></site_detail_url></location><location><api_detail_url><![CDATA[http://www.giantbomb.com/api/location/3035-343/]]></api_detail_url><id>343</id><name><![CDATA[China]]></name><site_detail_url><![CDATA[http://www.giantbomb.com/china/3035-343/]]></site_detail_url></location><location><api_detail_url><![CDATA[http://www.giantbomb.com/api/location/3035-396/]]></api_detail_url><id>396</id><name><![CDATA[The United States of America]]></name><site_detail_url><![CDATA[http://www.giantbomb.com/the-united-states-of-america/3035-396/]]></site_detail_url></location><location><api_detail_url><![CDATA[http://www.giantbomb.com/api/location/3035-293/]]></api_detail_url><id>293</id><name><![CDATA[Chicago]]></name><site_detail_url><![CDATA[http://www.giantbomb.com/chicago/3035-293/]]></site_detail_url></location><location><api_detail_url><![CDATA[http://www.giantbomb.com/api/location/3035-255/]]></api_detail_url><id>255</id><name><![CDATA[Washington, D.C.]]></name><site_detail_url><![CDATA[http://www.giantbomb.com/washington-dc/3035-255/]]></site_detail_url></location><location><api_detail_url><![CDATA[http://www.giantbomb.com/api/location/3035-984/]]></api_detail_url><id>984</id><name><![CDATA[Kalinatek Building]]></name><site_detail_url><![CDATA[http://www.giantbomb.com/kalinatek-building/3035-984/]]></site_detail_url></location><location><api_detail_url><![CDATA[http://www.giantbomb.com/api/location/3035-988/]]></api_detail_url><id>988</id><name><![CDATA[Langley]]></name><site_detail_url><![CDATA[http://www.giantbomb.com/langley/3035-988/]]></site_detail_url></location><location><api_detail_url><![CDATA[http://www.giantbomb.com/api/location/3035-989/]]></api_detail_url><id>989</id><name><![CDATA[Virginia]]></name><site_detail_url><![CDATA[http://www.giantbomb.com/virginia/3035-989/]]></site_detail_url></location><location><api_detail_url><![CDATA[http://www.giantbomb.com/api/location/3035-942/]]></api_detail_url><id>942</id><name><![CDATA[Missile Base]]></name><site_detail_url><![CDATA[http://www.giantbomb.com/missile-base/3035-942/]]></site_detail_url></location><location><api_detail_url><![CDATA[http://www.giantbomb.com/api/location/3035-1373/]]></api_detail_url><id>1373</id><name><![CDATA[Kansas]]></name><site_detail_url><![CDATA[http://www.giantbomb.com/kansas/3035-1373/]]></site_detail_url></location><location><api_detail_url><![CDATA[http://www.giantbomb.com/api/location/3035-1399/]]></api_detail_url><id>1399</id><name><![CDATA[Bank]]></name><site_detail_url><![CDATA[http://www.giantbomb.com/bank/3035-1399/]]></site_detail_url></location><location><api_detail_url><![CDATA[http://www.giantbomb.com/api/location/3035-420/]]></api_detail_url><id>420</id><name><![CDATA[Prison]]></name><site_detail_url><![CDATA[http://www.giantbomb.com/prison/3035-420/]]></site_detail_url></location><location><api_detail_url><![CDATA[http://www.giantbomb.com/api/location/3035-1443/]]></api_detail_url><id>1443</id><name><![CDATA[Jin Mao Tower]]></name><site_detail_url><![CDATA[http://www.giantbomb.com/jin-mao-tower/3035-1443/]]></site_detail_url></location><location><api_detail_url><![CDATA[http://www.giantbomb.com/api/location/3035-1444/]]></api_detail_url><id>1444</id><name><![CDATA[Ellsworth Prison]]></name><site_detail_url><![CDATA[http://www.giantbomb.com/ellsworth-prison/3035-1444/]]></site_detail_url></location><location><api_detail_url><![CDATA[http://www.giantbomb.com/api/location/3035-1890/]]></api_detail_url><id>1890</id><name><![CDATA[Cruise Ship]]></name><site_detail_url><![CDATA[http://www.giantbomb.com/cruise-ship/3035-1890/]]></site_detail_url></location><location><api_detail_url><![CDATA[http://www.giantbomb.com/api/location/3035-2369/]]></api_detail_url><id>2369</id><name><![CDATA[Israel]]></name><site_detail_url><![CDATA[http://www.giantbomb.com/israel/3035-2369/]]></site_detail_url></location><location><api_detail_url><![CDATA[http://www.giantbomb.com/api/location/3035-924/]]></api_detail_url><id>924</id><name><![CDATA[Casino]]></name><site_detail_url><![CDATA[http://www.giantbomb.com/casino/3035-924/]]></site_detail_url></location><location><api_detail_url><![CDATA[http://www.giantbomb.com/api/location/3035-2534/]]></api_detail_url><id>2534</id><name><![CDATA[Washington Monument]]></name><site_detail_url><![CDATA[http://www.giantbomb.com/washington-monument/3035-2534/]]></site_detail_url></location><location><api_detail_url><![CDATA[http://www.giantbomb.com/api/location/3035-1663/]]></api_detail_url><id>1663</id><name><![CDATA[Asia]]></name><site_detail_url><![CDATA[http://www.giantbomb.com/asia/3035-1663/]]></site_detail_url></location><location><api_detail_url><![CDATA[http://www.giantbomb.com/api/location/3035-65/]]></api_detail_url><id>65</id><name><![CDATA[Earth]]></name><site_detail_url><![CDATA[http://www.giantbomb.com/earth/3035-65/]]></site_detail_url></location></locations><objects><object><api_detail_url><![CDATA[http://www.giantbomb.com/api/object/3055-186/]]></api_detail_url><id>186</id><name><![CDATA[Night Vision Goggles]]></name><site_detail_url><![CDATA[http://www.giantbomb.com/night-vision-goggles/3055-186/]]></site_detail_url></object><object><api_detail_url><![CDATA[http://www.giantbomb.com/api/object/3055-379/]]></api_detail_url><id>379</id><name><![CDATA[Motion-Sensor Bomb]]></name><site_detail_url><![CDATA[http://www.giantbomb.com/motion-sensor-bomb/3055-379/]]></site_detail_url></object><object><api_detail_url><![CDATA[http://www.giantbomb.com/api/object/3055-405/]]></api_detail_url><id>405</id><name><![CDATA[SC-20K]]></name><site_detail_url><![CDATA[http://www.giantbomb.com/sc-20k/3055-405/]]></site_detail_url></object><object><api_detail_url><![CDATA[http://www.giantbomb.com/api/object/3055-432/]]></api_detail_url><id>432</id><name><![CDATA[Sticky Camera]]></name><site_detail_url><![CDATA[http://www.giantbomb.com/sticky-camera/3055-432/]]></site_detail_url></object><object><api_detail_url><![CDATA[http://www.giantbomb.com/api/object/3055-424/]]></api_detail_url><id>424</id><name><![CDATA[Lock Picks]]></name><site_detail_url><![CDATA[http://www.giantbomb.com/lock-picks/3055-424/]]></site_detail_url></object><object><api_detail_url><![CDATA[http://www.giantbomb.com/api/object/3055-118/]]></api_detail_url><id>118</id><name><![CDATA[Gun]]></name><site_detail_url><![CDATA[http://www.giantbomb.com/gun/3055-118/]]></site_detail_url></object><object><api_detail_url><![CDATA[http://www.giantbomb.com/api/object/3055-59/]]></api_detail_url><id>59</id><name><![CDATA[Pistol]]></name><site_detail_url><![CDATA[http://www.giantbomb.com/pistol/3055-59/]]></site_detail_url></object><object><api_detail_url><![CDATA[http://www.giantbomb.com/api/object/3055-621/]]></api_detail_url><id>621</id><name><![CDATA[Smoke Grenade]]></name><site_detail_url><![CDATA[http://www.giantbomb.com/smoke-grenade/3055-621/]]></site_detail_url></object><object><api_detail_url><![CDATA[http://www.giantbomb.com/api/object/3055-551/]]></api_detail_url><id>551</id><name><![CDATA[Flashbang]]></name><site_detail_url><![CDATA[http://www.giantbomb.com/flashbang/3055-551/]]></site_detail_url></object><object><api_detail_url><![CDATA[http://www.giantbomb.com/api/object/3055-426/]]></api_detail_url><id>426</id><name><![CDATA[Sticky Shockers]]></name><site_detail_url><![CDATA[http://www.giantbomb.com/sticky-shockers/3055-426/]]></site_detail_url></object><object><api_detail_url><![CDATA[http://www.giantbomb.com/api/object/3055-295/]]></api_detail_url><id>295</id><name><![CDATA[Knife]]></name><site_detail_url><![CDATA[http://www.giantbomb.com/knife/3055-295/]]></site_detail_url></object><object><api_detail_url><![CDATA[http://www.giantbomb.com/api/object/3055-111/]]></api_detail_url><id>111</id><name><![CDATA[Grenade]]></name><site_detail_url><![CDATA[http://www.giantbomb.com/grenade/3055-111/]]></site_detail_url></object><object><api_detail_url><![CDATA[http://www.giantbomb.com/api/object/3055-633/]]></api_detail_url><id>633</id><name><![CDATA[Rope]]></name><site_detail_url><![CDATA[http://www.giantbomb.com/rope/3055-633/]]></site_detail_url></object><object><api_detail_url><![CDATA[http://www.giantbomb.com/api/object/3055-413/]]></api_detail_url><id>413</id><name><![CDATA[Assault Rifle]]></name><site_detail_url><![CDATA[http://www.giantbomb.com/assault-rifle/3055-413/]]></site_detail_url></object><object><api_detail_url><![CDATA[http://www.giantbomb.com/api/object/3055-882/]]></api_detail_url><id>882</id><name><![CDATA[Ruger MK II]]></name><site_detail_url><![CDATA[http://www.giantbomb.com/ruger-mk-ii/3055-882/]]></site_detail_url></object><object><api_detail_url><![CDATA[http://www.giantbomb.com/api/object/3055-911/]]></api_detail_url><id>911</id><name><![CDATA[Gas Grenade]]></name><site_detail_url><![CDATA[http://www.giantbomb.com/gas-grenade/3055-911/]]></site_detail_url></object><object><api_detail_url><![CDATA[http://www.giantbomb.com/api/object/3055-980/]]></api_detail_url><id>980</id><name><![CDATA[Cochlear Implant]]></name><site_detail_url><![CDATA[http://www.giantbomb.com/cochlear-implant/3055-980/]]></site_detail_url></object><object><api_detail_url><![CDATA[http://www.giantbomb.com/api/object/3055-489/]]></api_detail_url><id>489</id><name><![CDATA[Silencer]]></name><site_detail_url><![CDATA[http://www.giantbomb.com/silencer/3055-489/]]></site_detail_url></object><object><api_detail_url><![CDATA[http://www.giantbomb.com/api/object/3055-1037/]]></api_detail_url><id>1037</id><name><![CDATA[Red Dot Sight]]></name><site_detail_url><![CDATA[http://www.giantbomb.com/red-dot-sight/3055-1037/]]></site_detail_url></object><object><api_detail_url><![CDATA[http://www.giantbomb.com/api/object/3055-869/]]></api_detail_url><id>869</id><name><![CDATA[Scuba Gear]]></name><site_detail_url><![CDATA[http://www.giantbomb.com/scuba-gear/3055-869/]]></site_detail_url></object><object><api_detail_url><![CDATA[http://www.giantbomb.com/api/object/3055-457/]]></api_detail_url><id>457</id><name><![CDATA[Laser Microphone]]></name><site_detail_url><![CDATA[http://www.giantbomb.com/laser-microphone/3055-457/]]></site_detail_url></object><object><api_detail_url><![CDATA[http://www.giantbomb.com/api/object/3055-1059/]]></api_detail_url><id>1059</id><name><![CDATA[SC Pistol]]></name><site_detail_url><![CDATA[http://www.giantbomb.com/sc-pistol/3055-1059/]]></site_detail_url></object><object><api_detail_url><![CDATA[http://www.giantbomb.com/api/object/3055-1045/]]></api_detail_url><id>1045</id><name><![CDATA[FN Five-Seven]]></name><site_detail_url><![CDATA[http://www.giantbomb.com/fn-five-seven/3055-1045/]]></site_detail_url></object><object><api_detail_url><![CDATA[http://www.giantbomb.com/api/object/3055-652/]]></api_detail_url><id>652</id><name><![CDATA[Air Duct]]></name><site_detail_url><![CDATA[http://www.giantbomb.com/air-duct/3055-652/]]></site_detail_url></object><object><api_detail_url><![CDATA[http://www.giantbomb.com/api/object/3055-1322/]]></api_detail_url><id>1322</id><name><![CDATA[FN F2000]]></name><site_detail_url><![CDATA[http://www.giantbomb.com/fn-f2000/3055-1322/]]></site_detail_url></object><object><api_detail_url><![CDATA[http://www.giantbomb.com/api/object/3055-83/]]></api_detail_url><id>83</id><name><![CDATA[Gold]]></name><site_detail_url><![CDATA[http://www.giantbomb.com/gold/3055-83/]]></site_detail_url></object><object><api_detail_url><![CDATA[http://www.giantbomb.com/api/object/3055-222/]]></api_detail_url><id>222</id><name><![CDATA[Riot Gun]]></name><site_detail_url><![CDATA[http://www.giantbomb.com/riot-gun/3055-222/]]></site_detail_url></object><object><api_detail_url><![CDATA[http://www.giantbomb.com/api/object/3055-1693/]]></api_detail_url><id>1693</id><name><![CDATA[Sneakers]]></name><site_detail_url><![CDATA[http://www.giantbomb.com/sneakers/3055-1693/]]></site_detail_url></object><object><api_detail_url><![CDATA[http://www.giantbomb.com/api/object/3055-1730/]]></api_detail_url><id>1730</id><name><![CDATA[EMP Grenade]]></name><site_detail_url><![CDATA[http://www.giantbomb.com/emp-grenade/3055-1730/]]></site_detail_url></object><object><api_detail_url><![CDATA[http://www.giantbomb.com/api/object/3055-1745/]]></api_detail_url><id>1745</id><name><![CDATA[Zip Line]]></name><site_detail_url><![CDATA[http://www.giantbomb.com/zip-line/3055-1745/]]></site_detail_url></object><object><api_detail_url><![CDATA[http://www.giantbomb.com/api/object/3055-114/]]></api_detail_url><id>114</id><name><![CDATA[Shotgun]]></name><site_detail_url><![CDATA[http://www.giantbomb.com/shotgun/3055-114/]]></site_detail_url></object><object><api_detail_url><![CDATA[http://www.giantbomb.com/api/object/3055-485/]]></api_detail_url><id>485</id><name><![CDATA[Mirror]]></name><site_detail_url><![CDATA[http://www.giantbomb.com/mirror/3055-485/]]></site_detail_url></object><object><api_detail_url><![CDATA[http://www.giantbomb.com/api/object/3055-586/]]></api_detail_url><id>586</id><name><![CDATA[Backpack]]></name><site_detail_url><![CDATA[http://www.giantbomb.com/backpack/3055-586/]]></site_detail_url></object><object><api_detail_url><![CDATA[http://www.giantbomb.com/api/object/3055-2766/]]></api_detail_url><id>2766</id><name><![CDATA[Snake Camera]]></name><site_detail_url><![CDATA[http://www.giantbomb.com/snake-camera/3055-2766/]]></site_detail_url></object><object><api_detail_url><![CDATA[http://www.giantbomb.com/api/object/3055-3587/]]></api_detail_url><id>3587</id><name><![CDATA[Sonar Goggles]]></name><site_detail_url><![CDATA[http://www.giantbomb.com/sonar-goggles/3055-3587/]]></site_detail_url></object><object><api_detail_url><![CDATA[http://www.giantbomb.com/api/object/3055-229/]]></api_detail_url><id>229</id><name><![CDATA[Pipe]]></name><site_detail_url><![CDATA[http://www.giantbomb.com/pipe/3055-229/]]></site_detail_url></object><object><api_detail_url><![CDATA[http://www.giantbomb.com/api/object/3055-68/]]></api_detail_url><id>68</id><name><![CDATA[Automated Sentry Gun]]></name><site_detail_url><![CDATA[http://www.giantbomb.com/automated-sentry-gun/3055-68/]]></site_detail_url></object><object><api_detail_url><![CDATA[http://www.giantbomb.com/api/object/3055-628/]]></api_detail_url><id>628</id><name><![CDATA[Binoculars]]></name><site_detail_url><![CDATA[http://www.giantbomb.com/binoculars/3055-628/]]></site_detail_url></object><object><api_detail_url><![CDATA[http://www.giantbomb.com/api/object/3055-1731/]]></api_detail_url><id>1731</id><name><![CDATA[Skorpion vz. 61]]></name><site_detail_url><![CDATA[http://www.giantbomb.com/skorpion-vz-61/3055-1731/]]></site_detail_url></object><object><api_detail_url><![CDATA[http://www.giantbomb.com/api/object/3055-1958/]]></api_detail_url><id>1958</id><name><![CDATA[Covert Machinegun]]></name><site_detail_url><![CDATA[http://www.giantbomb.com/covert-machinegun/3055-1958/]]></site_detail_url></object><object><api_detail_url><![CDATA[http://www.giantbomb.com/api/object/3055-4289/]]></api_detail_url><id>4289</id><name><![CDATA[Catsuit]]></name><site_detail_url><![CDATA[http://www.giantbomb.com/catsuit/3055-4289/]]></site_detail_url></object><object><api_detail_url><![CDATA[http://www.giantbomb.com/api/object/3055-634/]]></api_detail_url><id>634</id><name><![CDATA[Piano]]></name><site_detail_url><![CDATA[http://www.giantbomb.com/piano/3055-634/]]></site_detail_url></object></objects><people><person><api_detail_url><![CDATA[http://www.giantbomb.com/api/person/3040-61907/]]></api_detail_url><id>61907</id><name><![CDATA[Michael Ironside]]></name><site_detail_url><![CDATA[http://www.giantbomb.com/michael-ironside/3040-61907/]]></site_detail_url></person><person><api_detail_url><![CDATA[http://www.giantbomb.com/api/person/3040-15240/]]></api_detail_url><id>15240</id><name><![CDATA[Tom Clancy]]></name><site_detail_url><![CDATA[http://www.giantbomb.com/tom-clancy/3040-15240/]]></site_detail_url></person><person><api_detail_url><![CDATA[http://www.giantbomb.com/api/person/3040-89564/]]></api_detail_url><id>89564</id><name><![CDATA[Clint Hocking]]></name><site_detail_url><![CDATA[http://www.giantbomb.com/clint-hocking/3040-89564/]]></site_detail_url></person><person><api_detail_url><![CDATA[http://www.giantbomb.com/api/person/3040-10721/]]></api_detail_url><id>10721</id><name><![CDATA[Martin Kessler]]></name><site_detail_url><![CDATA[http://www.giantbomb.com/martin-kessler/3040-10721/]]></site_detail_url></person></people><platforms><platform><api_detail_url><![CDATA[http://www.giantbomb.com/api/platform/3045-23/]]></api_detail_url><id>23</id><name><![CDATA[GameCube]]></name><site_detail_url><![CDATA[http://www.giantbomb.com/gamecube/3045-23/]]></site_detail_url></platform><platform><api_detail_url><![CDATA[http://www.giantbomb.com/api/platform/3045-19/]]></api_detail_url><id>19</id><name><![CDATA[PlayStation 2]]></name><site_detail_url><![CDATA[http://www.giantbomb.com/playstation-2/3045-19/]]></site_detail_url></platform><platform><api_detail_url><![CDATA[http://www.giantbomb.com/api/platform/3045-34/]]></api_detail_url><id>34</id><name><![CDATA[N-Gage]]></name><site_detail_url><![CDATA[http://www.giantbomb.com/n-gage/3045-34/]]></site_detail_url></platform><platform><api_detail_url><![CDATA[http://www.giantbomb.com/api/platform/3045-94/]]></api_detail_url><id>94</id><name><![CDATA[PC]]></name><site_detail_url><![CDATA[http://www.giantbomb.com/pc/3045-94/]]></site_detail_url></platform><platform><api_detail_url><![CDATA[http://www.giantbomb.com/api/platform/3045-35/]]></api_detail_url><id>35</id><name><![CDATA[PlayStation 3]]></name><site_detail_url><![CDATA[http://www.giantbomb.com/playstation-3/3045-35/]]></site_detail_url></platform><platform><api_detail_url><![CDATA[http://www.giantbomb.com/api/platform/3045-4/]]></api_detail_url><id>4</id><name><![CDATA[Game Boy Advance]]></name><site_detail_url><![CDATA[http://www.giantbomb.com/game-boy-advance/3045-4/]]></site_detail_url></platform><platform><api_detail_url><![CDATA[http://www.giantbomb.com/api/platform/3045-32/]]></api_detail_url><id>32</id><name><![CDATA[Xbox]]></name><site_detail_url><![CDATA[http://www.giantbomb.com/xbox/3045-32/]]></site_detail_url></platform><platform><api_detail_url><![CDATA[http://www.giantbomb.com/api/platform/3045-20/]]></api_detail_url><id>20</id><name><![CDATA[Xbox 360]]></name><site_detail_url><![CDATA[http://www.giantbomb.com/xbox-360/3045-20/]]></site_detail_url></platform><platform><api_detail_url><![CDATA[http://www.giantbomb.com/api/platform/3045-86/]]></api_detail_url><id>86</id><name><![CDATA[Xbox Live Marketplace]]></name><site_detail_url><![CDATA[http://www.giantbomb.com/xbox-live-marketplace/3045-86/]]></site_detail_url></platform><platform><api_detail_url><![CDATA[http://www.giantbomb.com/api/platform/3045-52/]]></api_detail_url><id>52</id><name><![CDATA[Nintendo DS]]></name><site_detail_url><![CDATA[http://www.giantbomb.com/nintendo-ds/3045-52/]]></site_detail_url></platform><platform><api_detail_url><![CDATA[http://www.giantbomb.com/api/platform/3045-18/]]></api_detail_url><id>18</id><name><![CDATA[PlayStation Portable]]></name><site_detail_url><![CDATA[http://www.giantbomb.com/playstation-portable/3045-18/]]></site_detail_url></platform><platform><api_detail_url><![CDATA[http://www.giantbomb.com/api/platform/3045-36/]]></api_detail_url><id>36</id><name><![CDATA[Wii]]></name><site_detail_url><![CDATA[http://www.giantbomb.com/wii/3045-36/]]></site_detail_url></platform><platform><api_detail_url><![CDATA[http://www.giantbomb.com/api/platform/3045-96/]]></api_detail_url><id>96</id><name><![CDATA[iPhone]]></name><site_detail_url><![CDATA[http://www.giantbomb.com/iphone/3045-96/]]></site_detail_url></platform><platform><api_detail_url><![CDATA[http://www.giantbomb.com/api/platform/3045-17/]]></api_detail_url><id>17</id><name><![CDATA[Mac]]></name><site_detail_url><![CDATA[http://www.giantbomb.com/mac/3045-17/]]></site_detail_url></platform><platform><api_detail_url><![CDATA[http://www.giantbomb.com/api/platform/3045-117/]]></api_detail_url><id>117</id><name><![CDATA[Nintendo 3DS]]></name><site_detail_url><![CDATA[http://www.giantbomb.com/nintendo-3ds/3045-117/]]></site_detail_url></platform><platform><api_detail_url><![CDATA[http://www.giantbomb.com/api/platform/3045-124/]]></api_detail_url><id>124</id><name><![CDATA[Windows Phone]]></name><site_detail_url><![CDATA[http://www.giantbomb.com/windows-phone/3045-124/]]></site_detail_url></platform><platform><api_detail_url><![CDATA[http://www.giantbomb.com/api/platform/3045-88/]]></api_detail_url><id>88</id><name><![CDATA[PlayStation Network (PS3)]]></name><site_detail_url><![CDATA[http://www.giantbomb.com/playstation-network-ps3/3045-88/]]></site_detail_url></platform></platforms></results><version>1.0</version></response>
