<?xml version="1.0" encoding="utf-8"?>
<response><error><![CDATA[OK]]></error><limit>100</limit><offset>0</offset><number_of_page_results>6</number_of_page_results><number_of_total_results>6</number_of_total_results><status_code>1</status_code><results><release><api_detail_url><![CDATA[http://www.giantbomb.com/api/release/3050-84281/]]></api_detail_url><date_added>2009-06-06 15:20:09</date_added><date_last_updated>2009-06-06 15:20:09</date_last_updated><deck/><description/><expected_release_day/><expected_release_month/><expected_release_quarter/><expected_release_year/><game><api_detail_url><![CDATA[http://www.giantbomb.com/api/game/3030-4561/]]></api_detail_url><id>4561</id><name><![CDATA[Team Fortress Classic]]></name></game><game_rating><api_detail_url><![CDATA[http://www.giantbomb.com/api/game_rating/3065-16/]]></api_detail_url><id>16</id><name><![CDATA[ESRB: M]]></name></game_rating><id>84281</id><image><icon_url><![CDATA[http://static.giantbomb.com/uploads/square_avatar/1/14741/1047035-team_fortress_classic_box.jpg]]></icon_url><medium_url><![CDATA[http://static.giantbomb.com/uploads/scale_medium/1/14741/1047035-team_fortress_classic_box.jpg]]></medium_url><screen_url><![CDATA[http://static.giantbomb.com/uploads/screen_medium/1/14741/1047035-team_fortress_classic_box.jpg]]></screen_url><small_url><![CDATA[http://static.giantbomb.com/uploads/scale_small/1/14741/1047035-team_fortress_classic_box.jpg]]></small_url><super_url><![CDATA[http://static.giantbomb.com/uploads/scale_large/1/14741/1047035-team_fortress_classic_box.jpg]]></super_url><thumb_url><![CDATA[http://static.giantbomb.com/uploads/scale_avatar/1/14741/1047035-team_fortress_classic_box.jpg]]></thumb_url><tiny_url><![CDATA[http://static.giantbomb.com/uploads/square_mini/1/14741/1047035-team_fortress_classic_box.jpg]]></tiny_url></image><name><![CDATA[Team Fortress Classic]]></name><platform><api_detail_url><![CDATA[http://www.giantbomb.com/api/platform/3045-94/]]></api_detail_url><id>94</id><name><![CDATA[PC]]></name></platform><product_code_type/><product_code_value/><region><api_detail_url><![CDATA[http://www.giantbomb.com/api/region/3075-1/]]></api_detail_url><id>1</id><name><![CDATA[United States]]></name></region><release_date>1999-04-07 00:00:00</release_date><site_detail_url><![CDATA[http://www.giantbomb.com/team-fortress-classic/3030-4561/releases/#toc-release-84281]]></site_detail_url></release><release><api_detail_url><![CDATA[http://www.giantbomb.com/api/release/3050-95377/]]></api_detail_url><date_added>2010-04-22 03:24:50</date_added><date_last_updated>2010-04-22 03:25:55</date_last_updated><deck/><description/><expected_release_day/><expected_release_month/><expected_release_quarter/><expected_release_year/><game><api_detail_url><![CDATA[http://www.giantbomb.com/api/game/3030-4561/]]></api_detail_url><id>4561</id><name><![CDATA[Team Fortress Classic]]></name></game><game_rating/><id>95377</id><image/><name><![CDATA[Half-Life 1 Anthology]]></name><platform><api_detail_url><![CDATA[http://www.giantbomb.com/api/platform/3045-94/]]></api_detail_url><id>94</id><name><![CDATA[PC]]></name></platform><product_code_type><![CDATA[ISBN-10]]></product_code_type><product_code_value><![CDATA[0-7845-3889-1]]></product_code_value><region><api_detail_url><![CDATA[http://www.giantbomb.com/api/region/3075-1/]]></api_detail_url><id>1</id><name><![CDATA[United States]]></name></region><release_date>2005-09-26 00:00:00</release_date><site_detail_url><![CDATA[http://www.giantbomb.com/team-fortress-classic/3030-4561/releases/#toc-release-95377]]></site_detail_url></release><release><api_detail_url><![CDATA[http://www.giantbomb.com/api/release/3050-95378/]]></api_detail_url><date_added>2010-04-22 03:25:04</date_added><date_last_updated>2010-04-22 03:25:55</date_last_updated><deck/><description/><expected_release_day/><expected_release_month/><expected_release_quarter/><expected_release_year/><game><api_detail_url><![CDATA[http://www.giantbomb.com/api/game/3030-4561/]]></api_detail_url><id>4561</id><name><![CDATA[Team Fortress Classic]]></name></game><game_rating/><id>95378</id><image/><name><![CDATA[Half-Life 1 Anthology]]></name><platform><api_detail_url><![CDATA[http://www.giantbomb.com/api/platform/3045-94/]]></api_detail_url><id>94</id><name><![CDATA[PC]]></name></platform><product_code_type><![CDATA[EAN-13]]></product_code_type><product_code_value><![CDATA[4 521923 001517]]></product_code_value><region><api_detail_url><![CDATA[http://www.giantbomb.com/api/region/3075-6/]]></api_detail_url><id>6</id><name><![CDATA[Japan]]></name></region><release_date>2005-12-02 00:00:00</release_date><site_detail_url><![CDATA[http://www.giantbomb.com/team-fortress-classic/3030-4561/releases/#toc-release-95378]]></site_detail_url></release><release><api_detail_url><![CDATA[http://www.giantbomb.com/api/release/3050-95379/]]></api_detail_url><date_added>2010-04-22 03:25:24</date_added><date_last_updated>2010-04-22 03:25:24</date_last_updated><deck/><description/><expected_release_day/><expected_release_month/><expected_release_quarter/><expected_release_year/><game><api_detail_url><![CDATA[http://www.giantbomb.com/api/game/3030-4561/]]></api_detail_url><id>4561</id><name><![CDATA[Team Fortress Classic]]></name></game><game_rating><api_detail_url><![CDATA[http://www.giantbomb.com/api/game_rating/3065-2/]]></api_detail_url><id>2</id><name><![CDATA[PEGI: 16+]]></name></game_rating><id>95379</id><image><icon_url><![CDATA[http://static.giantbomb.com/uploads/square_avatar/1/13692/1345948-1172113703_00.jpg]]></icon_url><medium_url><![CDATA[http://static.giantbomb.com/uploads/scale_medium/1/13692/1345948-1172113703_00.jpg]]></medium_url><screen_url><![CDATA[http://static.giantbomb.com/uploads/screen_medium/1/13692/1345948-1172113703_00.jpg]]></screen_url><small_url><![CDATA[http://static.giantbomb.com/uploads/scale_small/1/13692/1345948-1172113703_00.jpg]]></small_url><super_url><![CDATA[http://static.giantbomb.com/uploads/scale_large/1/13692/1345948-1172113703_00.jpg]]></super_url><thumb_url><![CDATA[http://static.giantbomb.com/uploads/scale_avatar/1/13692/1345948-1172113703_00.jpg]]></thumb_url><tiny_url><![CDATA[http://static.giantbomb.com/uploads/square_mini/1/13692/1345948-1172113703_00.jpg]]></tiny_url></image><name><![CDATA[Half-Life 1 Anthology]]></name><platform><api_detail_url><![CDATA[http://www.giantbomb.com/api/platform/3045-94/]]></api_detail_url><id>94</id><name><![CDATA[PC]]></name></platform><product_code_type/><product_code_value/><region><api_detail_url><![CDATA[http://www.giantbomb.com/api/region/3075-2/]]></api_detail_url><id>2</id><name><![CDATA[United Kingdom]]></name></region><release_date/><site_detail_url><![CDATA[http://www.giantbomb.com/team-fortress-classic/3030-4561/releases/#toc-release-95379]]></site_detail_url></release><release><api_detail_url><![CDATA[http://www.giantbomb.com/api/release/3050-95382/]]></api_detail_url><date_added>2010-04-22 03:27:51</date_added><date_last_updated>2010-04-22 03:27:51</date_last_updated><deck/><description/><expected_release_day/><expected_release_month/><expected_release_quarter/><expected_release_year/><game><api_detail_url><![CDATA[http://www.giantbomb.com/api/game/3030-4561/]]></api_detail_url><id>4561</id><name><![CDATA[Team Fortress Classic]]></name></game><game_rating><api_detail_url><![CDATA[http://www.giantbomb.com/api/game_rating/3065-16/]]></api_detail_url><id>16</id><name><![CDATA[ESRB: M]]></name></game_rating><id>95382</id><image><icon_url><![CDATA[http://static.giantbomb.com/uploads/square_avatar/1/16191/493088-51dwmvyxj5l.jpg]]></icon_url><medium_url><![CDATA[http://static.giantbomb.com/uploads/scale_medium/1/16191/493088-51dwmvyxj5l.jpg]]></medium_url><screen_url><![CDATA[http://static.giantbomb.com/uploads/screen_medium/1/16191/493088-51dwmvyxj5l.jpg]]></screen_url><small_url><![CDATA[http://static.giantbomb.com/uploads/scale_small/1/16191/493088-51dwmvyxj5l.jpg]]></small_url><super_url><![CDATA[http://static.giantbomb.com/uploads/scale_large/1/16191/493088-51dwmvyxj5l.jpg]]></super_url><thumb_url><![CDATA[http://static.giantbomb.com/uploads/scale_avatar/1/16191/493088-51dwmvyxj5l.jpg]]></thumb_url><tiny_url><![CDATA[http://static.giantbomb.com/uploads/square_mini/1/16191/493088-51dwmvyxj5l.jpg]]></tiny_url></image><name><![CDATA[Half-Life: Initial Encounter]]></name><platform><api_detail_url><![CDATA[http://www.giantbomb.com/api/platform/3045-94/]]></api_detail_url><id>94</id><name><![CDATA[PC]]></name></platform><product_code_type/><product_code_value/><region><api_detail_url><![CDATA[http://www.giantbomb.com/api/region/3075-1/]]></api_detail_url><id>1</id><name><![CDATA[United States]]></name></region><release_date>1999-11-27 00:00:00</release_date><site_detail_url><![CDATA[http://www.giantbomb.com/team-fortress-classic/3030-4561/releases/#toc-release-95382]]></site_detail_url></release><release><api_detail_url><![CDATA[http://www.giantbomb.com/api/release/3050-95408/]]></api_detail_url><date_added>2010-04-22 03:29:47</date_added><date_last_updated>2010-04-22 03:29:47</date_last_updated><deck/><description/><expected_release_day/><expected_release_month/><expected_release_quarter/><expected_release_year/><game><api_detail_url><![CDATA[http://www.giantbomb.com/api/game/3030-4561/]]></api_detail_url><id>4561</id><name><![CDATA[Team Fortress Classic]]></name></game><game_rating><api_detail_url><![CDATA[http://www.giantbomb.com/api/game_rating/3065-16/]]></api_detail_url><id>16</id><name><![CDATA[ESRB: M]]></name></game_rating><id>95408</id><image><icon_url><![CDATA[http://static.giantbomb.com/uploads/square_avatar/3/34737/1027676-hlplat_front.jpg]]></icon_url><medium_url><![CDATA[http://static.giantbomb.com/uploads/scale_medium/3/34737/1027676-hlplat_front.jpg]]></medium_url><screen_url><![CDATA[http://static.giantbomb.com/uploads/screen_medium/3/34737/1027676-hlplat_front.jpg]]></screen_url><small_url><![CDATA[http://static.giantbomb.com/uploads/scale_small/3/34737/1027676-hlplat_front.jpg]]></small_url><super_url><![CDATA[http://static.giantbomb.com/uploads/scale_large/3/34737/1027676-hlplat_front.jpg]]></super_url><thumb_url><![CDATA[http://static.giantbomb.com/uploads/scale_avatar/3/34737/1027676-hlplat_front.jpg]]></thumb_url><tiny_url><![CDATA[http://static.giantbomb.com/uploads/square_mini/3/34737/1027676-hlplat_front.jpg]]></tiny_url></image><name><![CDATA[Half-Life Platinum Collection]]></name><platform><api_detail_url><![CDATA[http://www.giantbomb.com/api/platform/3045-94/]]></api_detail_url><id>94</id><name><![CDATA[PC]]></name></platform><product_code_type><![CDATA[ISBN-10]]></product_code_type><product_code_value><![CDATA[0-7849-2084-2]]></product_code_value><region><api_detail_url><![CDATA[http://www.giantbomb.com/api/region/3075-1/]]></api_detail_url><id>1</id><name><![CDATA[United States]]></name></region><release_date>2002-07-22 00:00:00</release_date><site_detail_url><![CDATA[http://www.giantbomb.com/team-fortress-classic/3030-4561/releases/#toc-release-95408]]></site_detail_url></release></results><version>1.0</version></response>
